aemonemdata/__init__.py
aemonemdata/aemonem.py
aemonemdata/constants.py
aemonemdata/exceptions.py
aemonemdata/str_enum.py
aemonemdata/utils.py
aemonemdata-2024.11.0.dist-info/LICENSE
aemonemdata-2024.11.0.dist-info/METADATA
aemonemdata-2024.11.0.dist-info/WHEEL
aemonemdata-2024.11.0.dist-info/top_level.txt
aemonemdata-2024.11.0.dist-info/RECORD
