Metadata-Version: 2.1
Name: aemonemdata
Version: 2024.11.0
Summary: Python Module to support Home Assistant integration with AEMO NEM Data
Author-email: Chris Abberley <unlisted@gmail.com>
Project-URL: Homepage, https://github.com/cabberley/aemonemdata
Project-URL: Issues, https://github.com/cabberley/aemonemdata/issues
Classifier: Programming Language :: Python :: 3
Classifier: Operating System :: OS Independent
Requires-Python: >=3.10
License-File: LICENSE
Requires-Dist: aiohttp>=3.8.1
Requires-Dist: asyncio
